LICENSE.txt
README.md
setup.cfg
setup.py
simple_conversion/__init__.py
simple_conversion/conversao.py
simple_conversion.egg-info/PKG-INFO
simple_conversion.egg-info/SOURCES.txt
simple_conversion.egg-info/dependency_links.txt
simple_conversion.egg-info/top_level.txt