Metadata-Version: 1.0
Name: simple-conversion
Version: 1.0.0
Summary: A data size converter
Home-page: UNKNOWN
Author: Danny Cuna
Author-email: dannyboycuna@gmail.com
License: MIT
Platform: UNKNOWN
